bispy/__init__.py
bispy/dovier_piazza_policriti/__init__.py
bispy/dovier_piazza_policriti/dovier_piazza_policriti.py
bispy/dovier_piazza_policriti/ranked_partition.py
bispy/paige_tarjan/__init__.py
bispy/paige_tarjan/compound_xblocks_container.py
bispy/paige_tarjan/paige_tarjan.py
bispy/saha/__init__.py
bispy/saha/ranked_compound_xblocks_container.py
bispy/saha/ranked_pta.py
bispy/saha/saha.py
bispy/saha/saha_partition.py
bispy/utilities/__init__.py
bispy/utilities/graph_decorator.py
bispy/utilities/graph_entities.py
bispy/utilities/graph_normalization.py
bispy/utilities/kosaraju.py
bispy/utilities/rank_computation.py
tests/__init__.py
tests/test_graph_entities.py
tests/test_graph_normalization.py
tests/test_init.py
tests/dovier_piazza_policriti/__init__.py
tests/dovier_piazza_policriti/dovier_piazza_policriti_test_cases.py
tests/dovier_piazza_policriti/test_dovier_piazza_policriti.py
tests/dovier_piazza_policriti/test_ranked_partition.py
tests/paige_tarjan/__init__.py
tests/paige_tarjan/paige_tarjan_test_cases.py
tests/paige_tarjan/rscp_utilities.py
tests/paige_tarjan/test_paige_tarjan.py
tests/paige_tarjan/test_rscp_utilities.py
tests/rank/__init__.py
tests/rank/rank_test_cases.py
tests/rank/test_kosaraju.py
tests/rank/test_rank.py
tests/saha/__init__.py
tests/saha/saha_test_cases.py
tests/saha/test_ranked_split.py
tests/saha/test_saha.py
tests/saha/test_saha_partition.py
tests/wf/__init__.py
tests/wf/test_well_foundedness.py
tests/wf/wf_test_cases.py
BisPy-0.2.2.dist-info/LICENSE
BisPy-0.2.2.dist-info/METADATA
BisPy-0.2.2.dist-info/WHEEL
BisPy-0.2.2.dist-info/top_level.txt
BisPy-0.2.2.dist-info/RECORD
