Metadata-Version: 2.1
Name: BisPy
Version: 0.2.2
Summary: A bisimulation library for Python
Home-page: https://github.com/fAndreuzzi/BisPy
Author: Francesco Andreuzzi
Author-email: andreuzzi.francesco@gmail.com
License: MIT
Project-URL: Bug Tracker, https://github.com/fAndreuzzi/BisPy/issues
Platform: UNKNOWN
Classifier: Programming Language :: Python :: 3
Classifier: License :: OSI Approved :: MIT License
Classifier: Operating System :: OS Independent
Classifier: Intended Audience :: Science/Research
Classifier: Topic :: Scientific/Engineering :: Mathematics
Requires-Python: >=3.5
License-File: LICENSE
Requires-Dist: networkx
Requires-Dist: llist
